pydbapi/__init__.py
pydbapi/api/__init__.py
pydbapi/api/mysql.py
pydbapi/api/pydbapimagic.py
pydbapi/api/redshift.py
pydbapi/api/snowflake.py
pydbapi/api/sqlite.py
pydbapi/api/trino.py
pydbapi/conf/__init__.py
pydbapi/conf/logconf.py
pydbapi/conf/myhandlers.py
pydbapi/db/__init__.py
pydbapi/db/base.py
pydbapi/db/fileexec.py
pydbapi/model/__init__.py
pydbapi/model/colmodel.py
pydbapi/model/resmodel.py
pydbapi/sql/__init__.py
pydbapi/sql/compile.py
pydbapi/sql/fileparse.py
pydbapi/sql/parse.py
pydbapi/sql/parse_old.py
pydbapi-0.0.141.dist-info/licenses/LICENSE
pydbapi-0.0.141.dist-info/METADATA
pydbapi-0.0.141.dist-info/WHEEL
pydbapi-0.0.141.dist-info/entry_points.txt
pydbapi-0.0.141.dist-info/top_level.txt
pydbapi-0.0.141.dist-info/RECORD
