Metadata-Version: 2.4
Name: pydbapi
Version: 0.0.141
Summary: A simple database API
Home-page: https://pypi.org/project/pydbapi/
Author: longfengpili
Author-email: 398745129@qq.com
Project-URL: Documentation, https://github.com/longfengpili/pydbapi/blob/master/README.md
Project-URL: Source, https://github.com/longfengpili/pydbapi
Keywords: dbapi,sqlite3,redshift,snowflake,doris,trino
Classifier: Programming Language :: Python :: 3
Classifier: License :: OSI Approved :: MIT License
Requires-Python: >=3.9
License-File: LICENSE
Requires-Dist: sqlparse
Requires-Dist: psycopg2-binary
Requires-Dist: pandas
Requires-Dist: pymysql
Requires-Dist: trino
Requires-Dist: colorlog
Requires-Dist: tqdm
Requires-Dist: ipython
Requires-Dist: trino
Dynamic: author
Dynamic: author-email
Dynamic: classifier
Dynamic: description
Dynamic: description-content-type
Dynamic: home-page
Dynamic: keywords
Dynamic: license-file
Dynamic: project-url
Dynamic: requires-dist
Dynamic: requires-python
Dynamic: summary
